NolanMQuantTradingEnvSetUp/__init__.py
NolanMQuantTradingEnvSetUp/setup.py
NolanMQuantTradingEnvSetUp-2.0.dist-info/METADATA
NolanMQuantTradingEnvSetUp-2.0.dist-info/WHEEL
NolanMQuantTradingEnvSetUp-2.0.dist-info/entry_points.txt
NolanMQuantTradingEnvSetUp-2.0.dist-info/top_level.txt
NolanMQuantTradingEnvSetUp-2.0.dist-info/RECORD
